{"__symbolic":"module","version":4,"metadata":{"Chess":{"__symbolic":"class","members":{"__ctor__":[{"__symbolic":"constructor","parameters":[{"__symbolic":"reference","name":"string"}]}],"clear":[{"__symbolic":"method"}],"reset":[{"__symbolic":"method"}],"load":[{"__symbolic":"method"}],"validate_fen":[{"__symbolic":"method"}],"generate_fen":[{"__symbolic":"method"}],"set_header":[{"__symbolic":"method"}],"update_setup":[{"__symbolic":"method"}],"get":[{"__symbolic":"method"}],"put":[{"__symbolic":"method"}],"remove":[{"__symbolic":"method"}],"build_move":[{"__symbolic":"method"}],"add_move":[{"__symbolic":"method"}],"generate_moves":[{"__symbolic":"method"}],"move_to_san":[{"__symbolic":"method"}],"stripped_san":[{"__symbolic":"method"}],"attacked":[{"__symbolic":"method"}],"king_attacked":[{"__symbolic":"method"}],"in_check":[{"__symbolic":"method"}],"in_checkmate":[{"__symbolic":"method"}],"in_stalemate":[{"__symbolic":"method"}],"insufficient_material":[{"__symbolic":"method"}],"in_threefold_repetition":[{"__symbolic":"method"}],"push":[{"__symbolic":"method"}],"make_move":[{"__symbolic":"method"}],"undo_move":[{"__symbolic":"method"}],"get_disambiguator":[{"__symbolic":"method"}],"ascii":[{"__symbolic":"method"}],"move_from_san":[{"__symbolic":"method"}],"rank":[{"__symbolic":"method"}],"file":[{"__symbolic":"method"}],"algebraic":[{"__symbolic":"method"}],"swap_color":[{"__symbolic":"method"}],"is_digit":[{"__symbolic":"method"}],"make_pretty":[{"__symbolic":"method"}],"clone":[{"__symbolic":"method"}],"trim":[{"__symbolic":"method"}],"perft":[{"__symbolic":"method"}],"getSquares":[{"__symbolic":"method"}],"getMoves":[{"__symbolic":"method"}],"getPgn":[{"__symbolic":"method"}],"load_pgn":[{"__symbolic":"method"}],"getHeader":[{"__symbolic":"method"}],"move":[{"__symbolic":"method"}],"undo":[{"__symbolic":"method"}],"square_color":[{"__symbolic":"method"}],"getHistory":[{"__symbolic":"method"}]}},"FenValidationResult":{"__symbolic":"class","members":{}},"ChessPiece":{"__symbolic":"class","members":{}},"Colour":{"WHITE":"w","BLACK":"b"},"PieceType":{"PAWN":"p","KNIGHT":"n","BISHOP":"b","ROOK":"r","QUEEN":"q","KING":"k"},"Move":{"__symbolic":"class","members":{"__ctor__":[{"__symbolic":"constructor","parameters":[{"__symbolic":"reference","name":"string"},{"__symbolic":"reference","name":"string"},{"__symbolic":"reference","name":"string"}]}]}}},"origins":{"Chess":"./lib/chess","FenValidationResult":"./lib/chess","ChessPiece":"./lib/chess","Colour":"./lib/chess-enums","PieceType":"./lib/chess-enums","Move":"./lib/chess-enums"},"importAs":"chess-ts"}